HBV/HBV_bmi.py
HBV/__init__.py
HBV/utils.py
hbv-1.5.2.dist-info/METADATA
hbv-1.5.2.dist-info/WHEEL
hbv-1.5.2.dist-info/licenses/LICENSE.txt
hbv-1.5.2.dist-info/RECORD
