Metadata-Version: 2.3
Name: HBV
Version: 1.5.2
Summary: Dev version for a HBV hydrological model using BMI for eWaterCycle.
Author-email: David Haasnoot <davidhaasnoot@gmail.com>
License-Expression: Apache-2.0
License-File: LICENSE.txt
Requires-Dist: bmipy
Requires-Dist: netcdf4
Requires-Dist: numpy
Requires-Dist: pandas
Requires-Dist: xarray
